tarexp/__init__.py
tarexp/base.py
tarexp/dataset.py
tarexp/evaluation.py
tarexp/experiments.py
tarexp/ledger.py
tarexp/util.py
tarexp/workflow.py
tarexp/component/__init__.py
tarexp/component/base.py
tarexp/component/labeler.py
tarexp/component/ranker.py
tarexp/component/sampler.py
tarexp/component/stopping.py
tarexp/helper/__init__.py
tarexp/helper/pandas_tools.py
tarexp/helper/plotting.py
tarexp-0.1.4.dist-info/LICENSE
tarexp-0.1.4.dist-info/METADATA
tarexp-0.1.4.dist-info/WHEEL
tarexp-0.1.4.dist-info/top_level.txt
tarexp-0.1.4.dist-info/RECORD
