Metadata-Version: 2.1
Name: tarexp
Version: 0.1.4
Summary: A Python framework for Technology-Assisted Review experiments.
Home-page: https://github.com/eugene-yang/tarexp
Author: Eugene Yang
Author-email: eugene.yang@jhu.edu
Requires-Python: >=3.7
License-File: LICENSE
Requires-Dist: numpy
Requires-Dist: pandas
Requires-Dist: scipy
Requires-Dist: tqdm
Requires-Dist: xxhash
Requires-Dist: ir-measures >=0.2.3
Requires-Dist: scikit-learn
